{
	"format_version": "1.10.0",
	"animation_controllers": {
		"controller.animation.drowned_necromancer.ranged": {
			"initial_state": "default",
			"states": {
				"attack": {
					"animations": [
						"attack"
					],
					"transitions": [
						{
							"default": "q.all_animations_finished&&!query.facing_target_to_range_attack"
						}
					],
					"blend_transition": 0.1
				},
				"default": {
					"transitions": [
						{
							"attack": "query.facing_target_to_range_attack"
						}
					],
					"blend_transition": 0.1
				}
			}
		}
	}
}